viberun/__init__.py
viberun/__main__.py
viberun/cli.py
viberun/vendor/aarch64-apple-darwin/viberun/viberun
viberun/vendor/aarch64-pc-windows-msvc/viberun/viberun.exe
viberun/vendor/aarch64-unknown-linux-musl/viberun/viberun
viberun/vendor/x86_64-apple-darwin/viberun/viberun
viberun/vendor/x86_64-pc-windows-msvc/viberun/viberun.exe
viberun/vendor/x86_64-unknown-linux-musl/viberun/viberun
viberun_dev-0.0.0.dev20260125213601.dist-info/licenses/LICENSE
viberun_dev-0.0.0.dev20260125213601.dist-info/METADATA
viberun_dev-0.0.0.dev20260125213601.dist-info/WHEEL
viberun_dev-0.0.0.dev20260125213601.dist-info/entry_points.txt
viberun_dev-0.0.0.dev20260125213601.dist-info/top_level.txt
viberun_dev-0.0.0.dev20260125213601.dist-info/RECORD
